shared_authentication/__init__.py
shared_authentication/authentication.py
shared_authentication/middleware.py
shared_authentication-0.1.2.dist-info/METADATA
shared_authentication-0.1.2.dist-info/WHEEL
shared_authentication-0.1.2.dist-info/top_level.txt
shared_authentication-0.1.2.dist-info/RECORD
