Metadata-Version: 2.2
Name: shared_authentication
Version: 0.1.2
Summary: A shared authentication package for Django microservices
Author: Shahroze Butt
Author-email: shahroze@techjkc.ca
Classifier: Programming Language :: Python :: 3
Classifier: Framework :: Django
Classifier: License :: OSI Approved :: MIT License
Classifier: Operating System :: OS Independent
Requires-Python: >=3.6
Requires-Dist: Django>=3.0
Requires-Dist: djangorestframework>=3.11
Dynamic: author
Dynamic: author-email
Dynamic: classifier
Dynamic: description
Dynamic: description-content-type
Dynamic: requires-dist
Dynamic: requires-python
Dynamic: summary
